setup.py
tempura.py
tempura.egg-info/PKG-INFO
tempura.egg-info/SOURCES.txt
tempura.egg-info/dependency_links.txt
tempura.egg-info/entry_points.txt
tempura.egg-info/not-zip-safe
tempura.egg-info/top_level.txt