Metadata-Version: 1.0
Name: tempura
Version: 0.1
Summary: not-a-template
Home-page: https://github.com/tengu/py-tempura
Author: UNKNOWN
Author-email: UNKNOWN
License: UNKNOWN
Platform: UNKNOWN
